bird_ospf_map/__init__.py
bird_ospf_map/cli.py
bird_ospf_map/helpers.py
bird_ospf_map/misc.py
bird_ospf_map-0.1.7.dist-info/LICENSE
bird_ospf_map-0.1.7.dist-info/METADATA
bird_ospf_map-0.1.7.dist-info/WHEEL
bird_ospf_map-0.1.7.dist-info/entry_points.txt
bird_ospf_map-0.1.7.dist-info/RECORD
