Metadata-Version: 2.3
Name: bird-ospf-map
Version: 0.1.7
Summary: 
Author: Pavel Dostál
Author-email: pdostal@pdostal.cz
Requires-Python: <4.0,>=3.11
Classifier: Programming Language :: Python :: 3
Classifier: Programming Language :: Python :: 3.11
Classifier: Programming Language :: Python :: 3.12
Classifier: Programming Language :: Python :: 3.13
Requires-Dist: argparse (>=1.4.0,<2.0.0)
Requires-Dist: click (>=8.1.8,<9.0.0)
Requires-Dist: paramiko (>=3.5.1,<4.0.0)
Requires-Dist: pathlib (>=1.0.1,<2.0.0)
Requires-Dist: pyyaml (>=6.0.2,<7.0.0)
